Metadata-Version: 2.1
Name: aift
Version: 1.3.1
Summary: AI for Thai Python Package
Home-page: https://github.com/AIforThai/aiforthai
Author: c-tawayip
Author-email: chuangk.piyawat@gmail.com
Classifier: Programming Language :: Python :: 3
Requires-Python: >=3.8
Requires-Dist: requests
Requires-Dist: pydub
Requires-Dist: pythainlp
Requires-Dist: python-crfsuite
